walnuts/__init__.py
walnuts/api_decorator.py
walnuts/cli.py
walnuts/config_manager.py
walnuts/email_report_template.html
walnuts/exceptions.py
walnuts/execute.py
walnuts/heman_datetime.py
walnuts/report.py
walnuts/swagger.py
walnuts/utils.py
walnuts/templates/.gitignore
walnuts/templates/.walnuts
walnuts/templates/README.md
walnuts/templates/app_for_test.py
walnuts/templates/config.yaml
walnuts/templates/requirements.txt
walnuts/templates/api/__init__.py
walnuts/templates/api/demo.py
walnuts/templates/common/__init__.py
walnuts/templates/common/assert_tools.py
walnuts/templates/db/__init__.py
walnuts/templates/report/.gitkeep
walnuts/templates/test_suites/__init__.py
walnuts/templates/test_suites/test_book_list.py
walnuts/templates/test_suites/test_login.py
walnuts-0.0.10.dist-info/LICENSE
walnuts-0.0.10.dist-info/METADATA
walnuts-0.0.10.dist-info/WHEEL
walnuts-0.0.10.dist-info/entry_points.txt
walnuts-0.0.10.dist-info/top_level.txt
walnuts-0.0.10.dist-info/RECORD
